ezflags/__init__.py
ezflags/exceptions.py
ezflags/flagparser.py
ezflags/ext/__init__.py
ezflags/ext/exflagparser.py
ezflags-1.4.2.dist-info/LICENSE
ezflags-1.4.2.dist-info/METADATA
ezflags-1.4.2.dist-info/WHEEL
ezflags-1.4.2.dist-info/top_level.txt
ezflags-1.4.2.dist-info/RECORD
