Metadata-Version: 2.1
Name: ezflags
Version: 1.4.2
Summary: A tool that makes creating command line flags super easy.
Home-page: https://github.com/karx1/ezflags
Author: karx
Author-email: nerdstep710@gmail.com
License: MIT
Project-URL: Documentation, https://ezflags.readthedocs.io/en/latest
Platform: UNKNOWN
Classifier: License :: OSI Approved :: MIT License
Classifier: Intended Audience :: Developers
Classifier: Natural Language :: English
Classifier: Operating System :: OS Independent
Requires-Python: >=3.6
Provides-Extra: docs
Requires-Dist: sphinx ; extra == 'docs'
Requires-Dist: sphinx-rtd-theme ; extra == 'docs'
